{"document": {"publication": "Tag My News", "full_text": "water quality in zhejiang province was returning to normal, officials said, more than two days after a truck collision led to a spill of carbolic acid that tainted drinking water for thousands.", "title": "asia: drinking water in chinese province returning to normal after spill", "line_count": 1, "filename": "10386", "publication_date": "08-06-2011 07:30:56", "lines_and_colors": [["water quality in zhejiang province was returning to normal, officials said, more than two days after a truck collision led to a spill of carbolic acid that tainted drinking water for thousands.", {}]]}}