{"document": {"publication": "Tag My News", "full_text": "javier morales hit an 89th-minute equalizer to give real salt lake a 2-2 draw at monterrey on wednesday in the first leg of the concacaf champions ...", "title": "morales helps real salt lake earn draw in concacaf final", "line_count": 1, "filename": "10605", "publication_date": "21-04-2011 18:37:55", "lines_and_colors": [["javier morales hit an 89th-minute equalizer to give real salt lake a 2-2 draw at monterrey on wednesday in the first leg of the concacaf champions ...", {}]]}}