{"document": {"publication": "Tag My News", "full_text": "the police in santiago have raided the home and offices of a lawyer representing a roman catholic priest found guilty by the vatican of sexually molesting under-age boys.", "title": "the americas: chile: evidence on priest seized", "line_count": 1, "filename": "10683", "publication_date": "20-04-2011 08:00:55", "lines_and_colors": [["the police in santiago have raided the home and offices of a lawyer representing a roman catholic priest found guilty by the vatican of sexually molesting under-age boys.", {}]]}}