{"document": {"publication": "Tag My News", "full_text": "the central intelligence agency has no intention of bringing home its chief operative in pakistan despite an apparent attempt by the pakistani media to unmask his identity, u.s. officials said on monday.", "title": "cia won't withdraw spy chief in pakistan: officials", "line_count": 1, "filename": "10760", "publication_date": "10-05-2011 00:19:42", "lines_and_colors": [["the central intelligence agency has no intention of bringing home its chief operative in pakistan despite an apparent attempt by the pakistani media to unmask his identity, u.s. officials said on monday.", {}]]}}