{"document": {"publication": "Tag My News", "full_text": "lockheed martin corp, the world's biggest aerospace company and the pentagon's no. 1 supplier by sales, has been hit by an unspecified cyber incident, the government said on saturday.", "title": "lockheed martin hit by cyber incident, u.s. says", "line_count": 1, "filename": "10881", "publication_date": "29-05-2011 01:47:14", "lines_and_colors": [["lockheed martin corp, the world's biggest aerospace company and the pentagon's no. 1 supplier by sales, has been hit by an unspecified cyber incident, the government said on saturday.", {}]]}}