{"document": {"publication": "Tag My News", "full_text": "top seed novak djokovic reached the serbia open final without hitting a ball on saturday after fellow serb janko tipsarevic pulled out of their semi-final with a thigh injury.", "title": "djokovic and lopez reach serbia open final", "line_count": 1, "filename": "1120", "publication_date": "30-04-2011 16:43:39", "lines_and_colors": [["top seed novak djokovic reached the serbia open final without hitting a ball on saturday after fellow serb janko tipsarevic pulled out of their semi-final with a thigh injury.", {}]]}}