{"document": {"publication": "Tag My News", "full_text": "paul holmes recalls an evening spent with ratko mladic, the former bosnian serb commander who was captured on thursday after 16 years on the run from genocide charges.", "title": "witness: an evening with ratko mladic", "line_count": 1, "filename": "11262", "publication_date": "26-05-2011 21:44:39", "lines_and_colors": [["paul holmes recalls an evening spent with ratko mladic, the former bosnian serb commander who was captured on thursday after 16 years on the run from genocide charges.", {}]]}}