{"document": {"publication": "Tag My News", "full_text": "the heads of bailed-out mortgage finance giants fannie mae  and freddie mac  were paid fat salaries without proper written procedures or analysis, according to a report published by the inspector general of the federal housing finance agency (fhfa-oig).", "title": "report critical of pay practices at fannie mae, freddie mac", "line_count": 1, "filename": "11401", "publication_date": "01-04-2011 07:21:58", "lines_and_colors": [["the heads of bailed-out mortgage finance giants fannie mae  and freddie mac  were paid fat salaries without proper written procedures or analysis, according to a report published by the inspector general of the federal housing finance agency (fhfa-oig).", {}]]}}