{"document": {"publication": "Tag My News", "full_text": "california should sell its claims to unpaid taxes to the private sector to raise money to bolster its finances, a state tax official said on monday.", "title": "california urged to sell its unpaid tax bills", "line_count": 1, "filename": "12031", "publication_date": "06-06-2011 21:31:56", "lines_and_colors": [["california should sell its claims to unpaid taxes to the private sector to raise money to bolster its finances, a state tax official said on monday.", {}]]}}