{"document": {"publication": "Tag My News", "full_text": "lehman brothers holdings inc  on wednesday agreed to put creditors' competing restructuring plans on the same timeline for court approval as its own plan, but reserved the right to raise future objections.", "title": "lehman, creditors agree on plan approval timeline", "line_count": 1, "filename": "12158", "publication_date": "13-04-2011 21:21:07", "lines_and_colors": [["lehman brothers holdings inc  on wednesday agreed to put creditors' competing restructuring plans on the same timeline for court approval as its own plan, but reserved the right to raise future objections.", {}]]}}