{"document": {"publication": "Tag My News", "full_text": "when david kirby travels, his poetry career always intrigues his seatmates. some wonder how he makes money. others wax nostalgic about their undergrad days.", "title": "frequent flier: a poetic job that invites conversation", "line_count": 1, "filename": "12727", "publication_date": "03-05-2011 07:14:36", "lines_and_colors": [["when david kirby travels, his poetry career always intrigues his seatmates. some wonder how he makes money. others wax nostalgic about their undergrad days.", {}]]}}