{"document": {"publication": "Tag My News", "full_text": "fox on tuesday officially named gus johnson as its lead play-by-play voice for the network's expanding college football and basketball cover ...", "title": "gus johnson officially joins fox", "line_count": 1, "filename": "1283", "publication_date": "11-05-2011 01:01:10", "lines_and_colors": [["fox on tuesday officially named gus johnson as its lead play-by-play voice for the network's expanding college football and basketball cover ...", {}]]}}