{"document": {"publication": "Tag My News", "full_text": "johnson &amp; johnson, following repeated u.s. recalls of tylenol and other nonprescription drugs in the past year, said it will make its u.s. over-the-counter business a separate organization.", "title": "j&j reorganizes consumer group in wake of recalls", "line_count": 1, "filename": "12959", "publication_date": "31-03-2011 02:22:47", "lines_and_colors": [["johnson &amp; johnson, following repeated u.s. recalls of tylenol and other nonprescription drugs in the past year, said it will make its u.s. over-the-counter business a separate organization.", {}]]}}