{"document": {"publication": "Tag My News", "full_text": "the mad scramble that is the opening week of the n.c.a.a. tournament makes way for a more orderly round of 16: eight games in two nights to whittle the field to eight.", "title": "ready for the round of 16", "line_count": 1, "filename": "13086", "publication_date": "24-03-2011 04:27:11", "lines_and_colors": [["the mad scramble that is the opening week of the n.c.a.a. tournament makes way for a more orderly round of 16: eight games in two nights to whittle the field to eight.", {}]]}}