{"document": {"publication": "Tag My News", "full_text": "there are 732 drivers in indianapolis 500 history from which to choose, but only a few were able to make indianapolis motor speedway's 100th ...", "title": "speedway selects top 33 drivers for the indianapolis 500", "line_count": 1, "filename": "13468", "publication_date": "15-05-2011 20:32:50", "lines_and_colors": [["there are 732 drivers in indianapolis 500 history from which to choose, but only a few were able to make indianapolis motor speedway's 100th ...", {}]]}}