{"document": {"publication": "Tag My News", "full_text": "globalive had no choice but to seek foreign funds for its wind mobile service and wants canada to loosen restrictions on outside influence quickly, its chairman said on thursday.", "title": "globalive urges canada to open up telecom sector", "line_count": 1, "filename": "13513", "publication_date": "02-06-2011 16:41:08", "lines_and_colors": [["globalive had no choice but to seek foreign funds for its wind mobile service and wants canada to loosen restrictions on outside influence quickly, its chairman said on thursday.", {}]]}}