{"document": {"publication": "Tag My News", "full_text": "goldman sachs  and others said they did not urge the tokyo stock exchange to halt trading because of japan's earthquake and subsequent nuclear crisis, despite a comment from the...", "title": "goldman, others: didn't seek tokyo exchange halt", "line_count": 1, "filename": "13681", "publication_date": "25-03-2011 21:47:03", "lines_and_colors": [["goldman sachs  and others said they did not urge the tokyo stock exchange to halt trading because of japan's earthquake and subsequent nuclear crisis, despite a comment from the...", {}]]}}