{"document": {"publication": "Tag My News", "full_text": "microsoft corp  is expected to report an 18 percent jump in quarterly profit on thursday, as its reliable windows and office franchises keep growing.", "title": "microsoft profit expected to rise, stock may not", "line_count": 1, "filename": "13884", "publication_date": "28-04-2011 06:15:14", "lines_and_colors": [["microsoft corp  is expected to report an 18 percent jump in quarterly profit on thursday, as its reliable windows and office franchises keep growing.", {}]]}}