{"document": {"publication": "Tag My News", "full_text": "russia's anna chakvetadze collapsed on court and retired from her first round match in stuttgart on tuesday, the third straight tournament she has pulled out of sick.", "title": "russian chakvetadze forced to pull out once again", "line_count": 1, "filename": "13969", "publication_date": "19-04-2011 20:51:40", "lines_and_colors": [["russia's anna chakvetadze collapsed on court and retired from her first round match in stuttgart on tuesday, the third straight tournament she has pulled out of sick.", {}]]}}