{"document": {"publication": "Tag My News", "full_text": "minmetals resources , china's biggest metals trading firm, on monday offered $6.5 billion to buy equinox minerals , chasing the target company's copper assets in zambia and saudi arabia.", "title": "china's minmetals offers $6.5 billion for equinox", "line_count": 1, "filename": "14069", "publication_date": "04-04-2011 12:41:00", "lines_and_colors": [["minmetals resources , china's biggest metals trading firm, on monday offered $6.5 billion to buy equinox minerals , chasing the target company's copper assets in zambia and saudi arabia.", {}]]}}