{"document": {"publication": "Tag My News", "full_text": "derek jeter needs 14 hits to get to 3,000 during the yankees' 10-game homestand, but that requires more than his monthlong pace of 1.18 hits a game.", "title": "to reach 3,000 in bronx, jeter must pick up the pace", "line_count": 1, "filename": "14252", "publication_date": "07-06-2011 08:00:59", "lines_and_colors": [["derek jeter needs 14 hits to get to 3,000 during the yankees' 10-game homestand, but that requires more than his monthlong pace of 1.18 hits a game.", {}]]}}