{"document": {"publication": "Tag My News", "full_text": "the final sliver of postseason hope for the milwaukee bucks went away wednesday night, that long-expected word coming while they played the miami ...", "title": "bucks play spoiler, knock off wade-less heat in miami", "line_count": 1, "filename": "14313", "publication_date": "07-04-2011 06:06:30", "lines_and_colors": [["the final sliver of postseason hope for the milwaukee bucks went away wednesday night, that long-expected word coming while they played the miami ...", {}]]}}