{"document": {"publication": "Tag My News", "full_text": "rafael nadal beat david ferrer 6-2, 6-4 in their second all-spanish final in two weeks to claim his sixth barcelona open title on sunday.", "title": "nadal rolls past ferrer to win barcelona open for sixth time", "line_count": 1, "filename": "14412", "publication_date": "25-04-2011 02:08:36", "lines_and_colors": [["rafael nadal beat david ferrer 6-2, 6-4 in their second all-spanish final in two weeks to claim his sixth barcelona open title on sunday.", {}]]}}