{"document": {"publication": "Tag My News", "full_text": "nato widened its campaign to weaken moammar gadhafi's regime with airstrikes on desert command centers and sea patrols to intercept ships.", "title": "nato widens libya pressure amid questions on goal", "line_count": 1, "filename": "14594", "publication_date": "21-05-2011 21:14:22", "lines_and_colors": [["nato widened its campaign to weaken moammar gadhafi's regime with airstrikes on desert command centers and sea patrols to intercept ships.", {}]]}}