{"document": {"publication": "Tag My News", "full_text": "cvs caremark corp's  former chief executive, thomas ryan, who recently retired after a 12-year tenure as ceo of the u.s. drugstore chain, took home more than $120 million in 2010.", "title": "cvs ex-ceo takes home over $120 million for 2010", "line_count": 1, "filename": "14688", "publication_date": "31-03-2011 10:42:51", "lines_and_colors": [["cvs caremark corp's  former chief executive, thomas ryan, who recently retired after a 12-year tenure as ceo of the u.s. drugstore chain, took home more than $120 million in 2010.", {}]]}}