{"document": {"publication": "Tag My News", "full_text": "a catholic monsignor, two priests and others named in the sexual abuse scandal rocking the archdiocese of philadelphia appeared in court on monday, where their defense tried unsuccessfully to have the presiding judge removed from the case.", "title": "accused in philadelphia church scandal appear in court", "line_count": 1, "filename": "14693", "publication_date": "14-03-2011 22:20:18", "lines_and_colors": [["a catholic monsignor, two priests and others named in the sexual abuse scandal rocking the archdiocese of philadelphia appeared in court on monday, where their defense tried unsuccessfully to have the presiding judge removed from the case.", {}]]}}