{"document": {"publication": "Tag My News", "full_text": "honolulu fire officials will try to determine the age and type of fireworks inside a bunker that exploded, killing five people, as they continue ...", "title": "company to be questioned monday over hawaii blast", "line_count": 1, "filename": "14703", "publication_date": "11-04-2011 00:51:33", "lines_and_colors": [["honolulu fire officials will try to determine the age and type of fireworks inside a bunker that exploded, killing five people, as they continue ...", {}]]}}