{"document": {"publication": "Tag My News", "full_text": "the obama administration is preparing a comprehensive proposal for corporate tax reform in an effort to kickstart the legislative process in congress, treasury secretary timothy geithner said on tuesday.", "title": "treasury working on corporate tax plan: geithner", "line_count": 1, "filename": "14811", "publication_date": "05-04-2011 18:58:14", "lines_and_colors": [["the obama administration is preparing a comprehensive proposal for corporate tax reform in an effort to kickstart the legislative process in congress, treasury secretary timothy geithner said on tuesday.", {}]]}}