{"document": {"publication": "Tag My News", "full_text": "stock investors head into next week with added worries about the sustainability of the recent rally and a desire to reduce risk, as shown by the stampede out of commodities on thursday.", "title": "commodities' drop curbs risk appetite", "line_count": 1, "filename": "14820", "publication_date": "07-05-2011 15:15:48", "lines_and_colors": [["stock investors head into next week with added worries about the sustainability of the recent rally and a desire to reduce risk, as shown by the stampede out of commodities on thursday.", {}]]}}