{"document": {"publication": "Tag My News", "full_text": "the 2010 preakness ad campaign urged young fans to \"get your preak on.\" this year, the second leg of racing's triple crown has a half-horse, ...", "title": "kegasus out front for preakness stakes", "line_count": 1, "filename": "15600", "publication_date": "31-03-2011 02:21:17", "lines_and_colors": [["the 2010 preakness ad campaign urged young fans to \"get your preak on.\" this year, the second leg of racing's triple crown has a half-horse, ...", {}]]}}