{"document": {"publication": "Tag My News", "full_text": "just a few days after his elder son prince william ties the knot with kate middleton, prince charles will make his way to d.c. on official business. ...", "title": "prince charles visiting the usa in may", "line_count": 1, "filename": "15793", "publication_date": "08-04-2011 15:31:00", "lines_and_colors": [["just a few days after his elder son prince william ties the knot with kate middleton, prince charles will make his way to d.c. on official business. ...", {}]]}}