{"document": {"publication": "Tag My News", "full_text": "carrie underwood will appear on a forthcoming randy travis duets album that celebrates his 25th anniversary of travis' country-music career. ...", "title": "carrie underwood to appear on randy travis duets album", "line_count": 1, "filename": "16003", "publication_date": "29-03-2011 16:37:00", "lines_and_colors": [["carrie underwood will appear on a forthcoming randy travis duets album that celebrates his 25th anniversary of travis' country-music career. ...", {}]]}}