{"document": {"publication": "Tag My News", "full_text": "the prosecutor in the assassination case of the former lebanese prime minister rafik hariri said he filed an expanded indictment on friday.", "title": "middle east: lebanon: hariri indictment grows", "line_count": 1, "filename": "16590", "publication_date": "12-03-2011 07:30:35", "lines_and_colors": [["the prosecutor in the assassination case of the former lebanese prime minister rafik hariri said he filed an expanded indictment on friday.", {}]]}}