{"document": {"publication": "Tag My News", "full_text": "tunisian authorities have ordered a curfew in a central mining town amid simmering unrest following deadly clashes between police and protesters, ...", "title": "tunisia orders curfew in restive mining town", "line_count": 1, "filename": "17068", "publication_date": "13-03-2011 21:23:47", "lines_and_colors": [["tunisian authorities have ordered a curfew in a central mining town amid simmering unrest following deadly clashes between police and protesters, ...", {}]]}}