{"document": {"publication": "Tag My News", "full_text": "the engineer, who won awards for his work developing catalysts that control auto emissions, is being held on charges of violating trade secrets, according to u.s. officials.", "title": "u.s. auto engineer in chinese custody for over a year", "line_count": 1, "filename": "17580", "publication_date": "17-12-2009 14:02:14", "lines_and_colors": [["the engineer, who won awards for his work developing catalysts that control auto emissions, is being held on charges of violating trade secrets, according to u.s. officials.", {}]]}}