{"document": {"publication": "Tag My News", "full_text": "right-wing lawmaker keiko fujimori has a small lead over left-wing nationalist ollanta humala ahead of peru's june 5 presidential run-off, a poll by survey firm ipsos showed on sunday.", "title": "peru's fujimori leads humala in presidential poll", "line_count": 1, "filename": "18720", "publication_date": "15-05-2011 12:06:08", "lines_and_colors": [["right-wing lawmaker keiko fujimori has a small lead over left-wing nationalist ollanta humala ahead of peru's june 5 presidential run-off, a poll by survey firm ipsos showed on sunday.", {}]]}}