{"document": {"publication": "Tag My News", "full_text": "the abbey of san clemente is so far the only monument from a list of 45 cultural landmarks to be fully restored since the earthquake that struck italy in 2009.", "title": "castiglione a casauria journal: abbey's restoration is first stitch to heal a gash in central italy's landscape", "line_count": 1, "filename": "18985", "publication_date": "05-05-2011 12:10:05", "lines_and_colors": [["the abbey of san clemente is so far the only monument from a list of 45 cultural landmarks to be fully restored since the earthquake that struck italy in 2009.", {}]]}}