{"document": {"publication": "Tag My News", "full_text": "more than 2.6 million pregnancies a year end in stillbirth, a tragedy which mostly hits women in poor countries and accounts for more deaths than aids and malaria combined, researchers said on wednesday.", "title": "stillbirth: a silent tragedy haunts the world's poor", "line_count": 1, "filename": "20346", "publication_date": "14-04-2011 00:34:33", "lines_and_colors": [["more than 2.6 million pregnancies a year end in stillbirth, a tragedy which mostly hits women in poor countries and accounts for more deaths than aids and malaria combined, researchers said on wednesday.", {}]]}}