{"document": {"publication": "Tag My News", "full_text": "thousands of mexicans on sunday marched into the capital city to protest the wave of killing that has claimed 38,000 lives since president felipe calderon launched his war on drug gangs in late 2006.", "title": "thousands of mexicans march to protest drug war", "line_count": 1, "filename": "20604", "publication_date": "08-05-2011 21:11:55", "lines_and_colors": [["thousands of mexicans on sunday marched into the capital city to protest the wave of killing that has claimed 38,000 lives since president felipe calderon launched his war on drug gangs in late 2006.", {}]]}}