{"document": {"publication": "Tag My News", "full_text": "with the washington capitals gaining steam in overtime, the tampa bay lightning converted two quick passes and put themselves a step closer to ...", "title": "lecavalier leads lightning past capitals 3-2 in overtime", "line_count": 1, "filename": "20752", "publication_date": "02-05-2011 06:42:30", "lines_and_colors": [["with the washington capitals gaining steam in overtime, the tampa bay lightning converted two quick passes and put themselves a step closer to ...", {}]]}}