{"document": {"publication": "Tag My News", "full_text": "motivated by french failures to respond quickly to the revolutions in tunisia and egypt, president nicolas sarkozy brought western allies together on libya.", "title": "sarkozy puts france at vanguard of west's war effort", "line_count": 1, "filename": "20778", "publication_date": "21-03-2011 13:50:08", "lines_and_colors": [["motivated by french failures to respond quickly to the revolutions in tunisia and egypt, president nicolas sarkozy brought western allies together on libya.", {}]]}}