{"document": {"publication": "Tag My News", "full_text": "a bomb targeting worshippers at a mosque killed at least five people and injured 30 in tikrit, north of the capital baghdad on friday, local police said.", "title": "bomb in iraqi city of tikrit kills at least five: police", "line_count": 1, "filename": "22533", "publication_date": "03-06-2011 12:55:13", "lines_and_colors": [["a bomb targeting worshippers at a mosque killed at least five people and injured 30 in tikrit, north of the capital baghdad on friday, local police said.", {}]]}}