{"document": {"publication": "Tag My News", "full_text": "new jersey must provide about $500 million for its poorer school districts next year, the state supreme court said on tuesday, complicating the state's ongoing budget negotiations.", "title": "new jersey must give poor schools $500 million: supreme court", "line_count": 1, "filename": "2273", "publication_date": "24-05-2011 20:37:35", "lines_and_colors": [["new jersey must provide about $500 million for its poorer school districts next year, the state supreme court said on tuesday, complicating the state's ongoing budget negotiations.", {}]]}}