{"document": {"publication": "Tag My News", "full_text": "colt mccoy is impressing mike holmgren, but the cleveland browns president isn't ready to hand over the reins of the starting qb job just ye ...", "title": "browns won't hand starting qb job to colt mccoy yet", "line_count": 1, "filename": "23508", "publication_date": "24-05-2011 21:14:00", "lines_and_colors": [["colt mccoy is impressing mike holmgren, but the cleveland browns president isn't ready to hand over the reins of the starting qb job just ye ...", {}]]}}