{"document": {"publication": "Tag My News", "full_text": "giovanni romano, a native of new york, is the chef at the backroom bistro in sioux center, iowa. his cooking has won over local residents, who keep coming back for more.", "title": "giving rural iowans a taste of italy", "line_count": 1, "filename": "2408", "publication_date": "02-04-2011 23:57:59", "lines_and_colors": [["giovanni romano, a native of new york, is the chef at the backroom bistro in sioux center, iowa. his cooking has won over local residents, who keep coming back for more.", {}]]}}