{"document": {"publication": "Tag My News", "full_text": "former world number one amelie mauresmo has been barred from playing the french open mixed doubles because she is not registered in the anti-doping program, organizers said on wednesday.", "title": "open-mauresmo barred from mixed doubles over anti-doping", "line_count": 1, "filename": "24977", "publication_date": "25-05-2011 22:31:42", "lines_and_colors": [["former world number one amelie mauresmo has been barred from playing the french open mixed doubles because she is not registered in the anti-doping program, organizers said on wednesday.", {}]]}}