{"document": {"publication": "Tag My News", "full_text": "the international criminal court prosecutor said on wednesday he will request arrest warrants for the killing of pro-democracy demonstrators in libya, and u.n. envoys said one target could be libyan leader muammar gaddafi.", "title": "icc prosecutor seeks 3 arrest warrants on libya", "line_count": 1, "filename": "25487", "publication_date": "04-05-2011 22:54:35", "lines_and_colors": [["the international criminal court prosecutor said on wednesday he will request arrest warrants for the killing of pro-democracy demonstrators in libya, and u.n. envoys said one target could be libyan leader muammar gaddafi.", {}]]}}