{"document": {"publication": "Tag My News", "full_text": "the chicago bears have no lingering questions about jay cutler. coach lovie smith, still smarting from what he perceived as unfair criticism ...", "title": "lovie smith: no question bears are committed to jay cutler", "line_count": 1, "filename": "2559", "publication_date": "24-03-2011 17:49:00", "lines_and_colors": [["the chicago bears have no lingering questions about jay cutler. coach lovie smith, still smarting from what he perceived as unfair criticism ...", {}]]}}