{"document": {"publication": "Tag My News", "full_text": "international health alliance gavi is seeking $3.7 billion from a june 13 pledging conference in london to help deliver vaccines to nearly a quarter of a billion children across the world by 2015.", "title": "vaccine alliance seeks $3.7 bln from london meeting", "line_count": 1, "filename": "25763", "publication_date": "30-05-2011 15:22:16", "lines_and_colors": [["international health alliance gavi is seeking $3.7 billion from a june 13 pledging conference in london to help deliver vaccines to nearly a quarter of a billion children across the world by 2015.", {}]]}}