{"document": {"publication": "Tag My News", "full_text": "unstoppable so far this season, novak djokovic will put his perfect 17-0 record on the line against world number one rafa nadal in sunday's final of the indian wells atp tournament.", "title": "top seed nadal next target for unstoppable djokovic", "line_count": 1, "filename": "26508", "publication_date": "20-03-2011 02:47:00", "lines_and_colors": [["unstoppable so far this season, novak djokovic will put his perfect 17-0 record on the line against world number one rafa nadal in sunday's final of the indian wells atp tournament.", {}]]}}