{"document": {"publication": "Tag My News", "full_text": "carl edwards held on to win the nationwide series at dover international speedway on saturday after a wreck-filled final lap that knocked out ...", "title": "carl edwards wins nationwide race at dover", "line_count": 1, "filename": "26590", "publication_date": "15-05-2011 01:48:46", "lines_and_colors": [["carl edwards held on to win the nationwide series at dover international speedway on saturday after a wreck-filled final lap that knocked out ...", {}]]}}