{"document": {"publication": "Tag My News", "full_text": "microsoft's $8.5 billion acquisition of skype is likely to boost videoconferencing from workers' desktops, posing further risks to video technology providers like polycom and logitech.", "title": "skype deal raises risks for videoconferencing firms", "line_count": 1, "filename": "27168", "publication_date": "12-05-2011 22:22:37", "lines_and_colors": [["microsoft's $8.5 billion acquisition of skype is likely to boost videoconferencing from workers' desktops, posing further risks to video technology providers like polycom and logitech.", {}]]}}