{"document": {"publication": "Tag My News", "full_text": "phoebe snow, a bluesy singer, guitarist and songwriter who had a defining hit of the 1970s with poetry man but then largely dropped out of the ...", "title": "'poetry man' singer phoebe snow dies at 58", "line_count": 1, "filename": "27942", "publication_date": "26-04-2011 17:54:11", "lines_and_colors": [["phoebe snow, a bluesy singer, guitarist and songwriter who had a defining hit of the 1970s with poetry man but then largely dropped out of the ...", {}]]}}