{"document": {"publication": "Tag My News", "full_text": "using a multitude of statistical categories, a case could be made that monday's n.c.a.a. men's championship game was the worst in tournament history.", "title": "connecticut and butler saved worst for last", "line_count": 1, "filename": "29233", "publication_date": "06-04-2011 08:20:05", "lines_and_colors": [["using a multitude of statistical categories, a case could be made that monday's n.c.a.a. men's championship game was the worst in tournament history.", {}]]}}