{"document": {"publication": "Tag My News", "full_text": "kevin durant scored 19 points, reserve daequan cook added 18 and the oklahoma city thunder followed their triple-overtime triumph with a 99-72 ...", "title": "durant, thunder win big, push grizzlies to brink of elimination", "line_count": 1, "filename": "29287", "publication_date": "12-05-2011 17:57:29", "lines_and_colors": [["kevin durant scored 19 points, reserve daequan cook added 18 and the oklahoma city thunder followed their triple-overtime triumph with a 99-72 ...", {}]]}}