{"document": {"publication": "Tag My News", "full_text": "sudan decided to create two additional states in darfur, state media said on thursday in what rebels have condemned as plan to strengthen khartoum's control over the troubled western region.", "title": "sudan divides darfur in five smaller states", "line_count": 1, "filename": "30243", "publication_date": "05-05-2011 20:28:33", "lines_and_colors": [["sudan decided to create two additional states in darfur, state media said on thursday in what rebels have condemned as plan to strengthen khartoum's control over the troubled western region.", {}]]}}