{"document": {"publication": "Tag My News", "full_text": "the database, listing more than half a million pieces of property, is part of a new project, financed by the israeli government, to harness technology in the struggle for restitution.", "title": "jerusalem journal: property lost in holocaust is cataloged online", "line_count": 1, "filename": "30330", "publication_date": "03-05-2011 16:31:10", "lines_and_colors": [["the database, listing more than half a million pieces of property, is part of a new project, financed by the israeli government, to harness technology in the struggle for restitution.", {}]]}}