{"document": {"publication": "Tag My News", "full_text": "the increase in levels of radioactive materials in seawater raised the possibility of new leaks at the fukushima daiichi nuclear plant, the government said.", "title": "levels of radioactive materials rise near japanese plant", "line_count": 1, "filename": "30341", "publication_date": "17-04-2011 03:40:32", "lines_and_colors": [["the increase in levels of radioactive materials in seawater raised the possibility of new leaks at the fukushima daiichi nuclear plant, the government said.", {}]]}}