{"document": {"publication": "Tag My News", "full_text": "an oscar-winning special effects expert was cleared monday of health and safety breaches after a cameraman died during the making of the last batman movie in 2007.", "title": "special effects expert cleared of '07 batman death", "line_count": 1, "filename": "33274", "publication_date": "14-03-2011 21:19:29", "lines_and_colors": [["an oscar-winning special effects expert was cleared monday of health and safety breaches after a cameraman died during the making of the last batman movie in 2007.", {}]]}}