{"document": {"publication": "Tag My News", "full_text": "a jamaican financier who ran a ponzi scheme that defrauded thousands of investors in florida and the caribbean out of more than $220 million pleaded guilty on tuesday to fraud and money laundering charges in a u.s. court.", "title": "caribbean ponzi schemer pleads guilty in u.s. court", "line_count": 1, "filename": "33374", "publication_date": "29-03-2011 21:22:19", "lines_and_colors": [["a jamaican financier who ran a ponzi scheme that defrauded thousands of investors in florida and the caribbean out of more than $220 million pleaded guilty on tuesday to fraud and money laundering charges in a u.s. court.", {}]]}}