{"document": {"publication": "Tag My News", "full_text": "a woman who missed a connecting flight at denver international airport said she was raped in a deserted concourse by a man she met at an airport ...", "title": "woman says she was raped in denver airport, employees walked by", "line_count": 1, "filename": "33421", "publication_date": "13-04-2011 21:05:59", "lines_and_colors": [["a woman who missed a connecting flight at denver international airport said she was raped in a deserted concourse by a man she met at an airport ...", {}]]}}