{"document": {"publication": "Tag My News", "full_text": "a nearly two-week layoff didn't bother connecticut. the huskies took to a familiar script, routing a first-round opponent in the ncaa women's ...", "title": "top-seeded uconn routs hartford in tournament opener", "line_count": 1, "filename": "33518", "publication_date": "20-03-2011 21:31:51", "lines_and_colors": [["a nearly two-week layoff didn't bother connecticut. the huskies took to a familiar script, routing a first-round opponent in the ncaa women's ...", {}]]}}