{"document": {"publication": "Tag My News", "full_text": "scotty mccreery and lauren alaina had the best-selling downloads in country music last week, as the singles for both singers topped 100,000. ...", "title": "scotty mccreery, lauren alaina tracks top country sales", "line_count": 1, "filename": "33540", "publication_date": "01-06-2011 18:48:00", "lines_and_colors": [["scotty mccreery and lauren alaina had the best-selling downloads in country music last week, as the singles for both singers topped 100,000. ...", {}]]}}