{"document": {"publication": "Tag My News", "full_text": "world number one rafa nadal moved into the quarter-finals of the madrid open without hitting a shot on thursday after his third-round opponent juan martin del potro withdrew from the clay event with a hip injury.", "title": "nadal through in madrid after del potro quits", "line_count": 1, "filename": "33767", "publication_date": "05-05-2011 23:14:26", "lines_and_colors": [["world number one rafa nadal moved into the quarter-finals of the madrid open without hitting a shot on thursday after his third-round opponent juan martin del potro withdrew from the clay event with a hip injury.", {}]]}}