{"document": {"publication": "Tag My News", "full_text": "japan's central bank on monday rushed to bolster markets in the wake of the country's worst disaster since world war two and although the authorities said it was too early to put a...", "title": "japan economy shudders after shocks, boj pumps cash", "line_count": 1, "filename": "33867", "publication_date": "15-03-2011 05:28:20", "lines_and_colors": [["japan's central bank on monday rushed to bolster markets in the wake of the country's worst disaster since world war two and although the authorities said it was too early to put a...", {}]]}}