{"document": {"publication": "Tag My News", "full_text": "'true blood' beefcake alexander skarsg??rd, 34, opens up about his hot cast -- and opens up his sleek shirt -- in the june issue of 'gq'.", "title": "alexander skarsg??rd: 'true blood' love scenes take 'a lot of acting'", "line_count": 1, "filename": "33939", "publication_date": "17-05-2011 21:18:00", "lines_and_colors": [["'true blood' beefcake alexander skarsg??rd, 34, opens up about his hot cast -- and opens up his sleek shirt -- in the june issue of 'gq'.", {}]]}}