{"document": {"publication": "Tag My News", "full_text": "nasa on monday cleared space shuttle endeavour for a second launch attempt on may 16 to deliver a pioneering physics experiment and spare parts to the international space station.", "title": "nasa repairs shuttle problem and sets may 16 launch", "line_count": 1, "filename": "34122", "publication_date": "09-05-2011 23:54:16", "lines_and_colors": [["nasa on monday cleared space shuttle endeavour for a second launch attempt on may 16 to deliver a pioneering physics experiment and spare parts to the international space station.", {}]]}}