{"document": {"publication": "Tag My News", "full_text": "the national weather service warned on monday of the imminent failure of a levee on the black river in southeast missouri, prompting a mandatory evacuation of about 1,000 people in poplar bluff.", "title": "floods force evacuations in ohio valley, missouri", "line_count": 1, "filename": "34171", "publication_date": "26-04-2011 00:13:46", "lines_and_colors": [["the national weather service warned on monday of the imminent failure of a levee on the black river in southeast missouri, prompting a mandatory evacuation of about 1,000 people in poplar bluff.", {}]]}}