{"document": {"publication": "Tag My News", "full_text": "as of sunday, the federal government will no longer issue paper social security checks to new applicants and will instead be using electronic deposits.", "title": "beginning of the end for paper social security checks", "line_count": 1, "filename": "34241", "publication_date": "29-04-2011 18:59:59", "lines_and_colors": [["as of sunday, the federal government will no longer issue paper social security checks to new applicants and will instead be using electronic deposits.", {}]]}}