{"document": {"publication": "Tag My News", "full_text": "choi geesung was named chief executive, and jay y. lee, son of the former group chairman lee kun-hee, was named to the new post of chief operating officer.", "title": "management shakeup at samsung electronics", "line_count": 1, "filename": "4132", "publication_date": "16-12-2009 08:27:41", "lines_and_colors": [["choi geesung was named chief executive, and jay y. lee, son of the former group chairman lee kun-hee, was named to the new post of chief operating officer.", {}]]}}