{"document": {"publication": "Tag My News", "full_text": "the state of new jersey has reached an agreement that will keep two of its horse racing tracks in business by placing them in private hands, officials said.", "title": "new jersey makes deal to put racing tracks in private hands", "line_count": 1, "filename": "4140", "publication_date": "14-05-2011 00:06:32", "lines_and_colors": [["the state of new jersey has reached an agreement that will keep two of its horse racing tracks in business by placing them in private hands, officials said.", {}]]}}