{"document": {"publication": "Tag My News", "full_text": "the thoroughbred retirement foundation was completing its review, saying that dr. stacey huntington's evaluation of the horses previously under its care was incomplete.", "title": "veterinarian urges foundation's overhaul", "line_count": 1, "filename": "475", "publication_date": "08-04-2011 08:40:05", "lines_and_colors": [["the thoroughbred retirement foundation was completing its review, saying that dr. stacey huntington's evaluation of the horses previously under its care was incomplete.", {}]]}}