{"document": {"publication": "Tag My News", "full_text": "restaurant chains will have to tell you how many calories are in your sandwich, your milk shake and even your bag of chips by the middle of next year as part of the u.s. government's fight against obesity.", "title": "what's in your sandwich? u.s. wants you to know", "line_count": 1, "filename": "5368", "publication_date": "02-04-2011 01:36:32", "lines_and_colors": [["restaurant chains will have to tell you how many calories are in your sandwich, your milk shake and even your bag of chips by the middle of next year as part of the u.s. government's fight against obesity.", {}]]}}