{"document": {"publication": "Tag My News", "full_text": "u.s. aviation authorities further shook up air traffic management on friday following embarrassing incidents involving sleeping controllers and mistakes handling first lady michelle obama's plane.", "title": "faa shakes up air traffic control management", "line_count": 1, "filename": "5571", "publication_date": "29-04-2011 17:57:00", "lines_and_colors": [["u.s. aviation authorities further shook up air traffic management on friday following embarrassing incidents involving sleeping controllers and mistakes handling first lady michelle obama's plane.", {}]]}}