{"document": {"publication": "Tag My News", "full_text": "a bill passed in the texas house would slash $23 billion from the current level of spending over the next two-year budget cycle ' a 12.3 percent reduction.", "title": "after years of cost cuts, texas tries to find more", "line_count": 1, "filename": "5679", "publication_date": "09-04-2011 16:01:08", "lines_and_colors": [["a bill passed in the texas house would slash $23 billion from the current level of spending over the next two-year budget cycle ' a 12.3 percent reduction.", {}]]}}