{"document": {"publication": "Tag My News", "full_text": "color is the building block of style this spring, literally. the color blocking craze mixes large swaths of color for an effect that is both ...", "title": "color blocking makes an un-square style statement", "line_count": 1, "filename": "6310", "publication_date": "18-03-2011 01:14:08", "lines_and_colors": [["color is the building block of style this spring, literally. the color blocking craze mixes large swaths of color for an effect that is both ...", {}]]}}