{"document": {"publication": "Tag My News", "full_text": "the high-flying orioles were brought down to earth by a two-game new york yankees sweep but baltimore looked to rise again friday by handing the ball to one of their top reasons for optimism, pitcher zach britton.", "title": "britton fuels optimism for baltimore's rising orioles", "line_count": 1, "filename": "6450", "publication_date": "15-04-2011 19:45:04", "lines_and_colors": [["the high-flying orioles were brought down to earth by a two-game new york yankees sweep but baltimore looked to rise again friday by handing the ball to one of their top reasons for optimism, pitcher zach britton.", {}]]}}