{"document": {"publication": "Tag My News", "full_text": "the family of the giants fan brutally beaten in the dodger stadium parking lot on opening day is suing the  dodgers, according to news media ...", "title": "family of beaten giants fan suing dodgers", "line_count": 1, "filename": "6907", "publication_date": "24-05-2011 21:03:00", "lines_and_colors": [["the family of the giants fan brutally beaten in the dodger stadium parking lot on opening day is suing the  dodgers, according to news media ...", {}]]}}