{"document": {"publication": "Tag My News", "full_text": "egypt thursday took another step toward erasing the legacy of deposed president hosni mubarak by ordering his name, and that of his family, removed from public institutions across the nation.", "title": "egypt orders \"pharaoh\" mubarak's name stripped off", "line_count": 1, "filename": "7899", "publication_date": "21-04-2011 23:39:54", "lines_and_colors": [["egypt thursday took another step toward erasing the legacy of deposed president hosni mubarak by ordering his name, and that of his family, removed from public institutions across the nation.", {}]]}}