{"document": {"publication": "Tag My News", "full_text": "florida beat san francisco 1-0 on thursday to complete a rare three-game sweep over the giants and add insult to injury for the reigning world series champions.", "title": "marlins add to giants' day of misery", "line_count": 1, "filename": "8978", "publication_date": "27-05-2011 03:29:53", "lines_and_colors": [["florida beat san francisco 1-0 on thursday to complete a rare three-game sweep over the giants and add insult to injury for the reigning world series champions.", {}]]}}