{"document": {"publication": "Tag My News", "full_text": "wisconsin governor scott walker released on wednesday bond restructuring and other plans to close a current year budget gap that were cut from a controversial law to curb the powers of public sector unions.", "title": "wisconsin governor releases bond restructuring bill", "line_count": 1, "filename": "9777", "publication_date": "31-03-2011 06:22:57", "lines_and_colors": [["wisconsin governor scott walker released on wednesday bond restructuring and other plans to close a current year budget gap that were cut from a controversial law to curb the powers of public sector unions.", {}]]}}