{"document": {"publication": "Tag My News", "full_text": "as pavel datsyuk turned game 2 of his western conference quarterfinals into his personal circus act, someone on twitter jokingly suggested that ...", "title": "datsyuk dazzles, red wings hold on for 2-0 series lead", "line_count": 1, "filename": "9998", "publication_date": "17-04-2011 00:48:26", "lines_and_colors": [["as pavel datsyuk turned game 2 of his western conference quarterfinals into his personal circus act, someone on twitter jokingly suggested that ...", {}]]}}